orbax/checkpoint/__init__.py
orbax/checkpoint/abstract_checkpoint_manager.py
orbax/checkpoint/aggregate_handlers.py
orbax/checkpoint/args.py
orbax/checkpoint/arrays.py
orbax/checkpoint/checkpoint_args.py
orbax/checkpoint/checkpoint_manager.py
orbax/checkpoint/checkpoint_managers.py
orbax/checkpoint/checkpoint_utils.py
orbax/checkpoint/checkpointers.py
orbax/checkpoint/conftest.py
orbax/checkpoint/future.py
orbax/checkpoint/handlers.py
orbax/checkpoint/msgpack_utils.py
orbax/checkpoint/options.py
orbax/checkpoint/path.py
orbax/checkpoint/pathways.py
orbax/checkpoint/test_utils.py
orbax/checkpoint/transform_utils.py
orbax/checkpoint/tree.py
orbax/checkpoint/type_handlers.py
orbax/checkpoint/utils.py
orbax/checkpoint/version.py
orbax/checkpoint/_src/README.md
orbax/checkpoint/_src/asyncio_utils.py
orbax/checkpoint/_src/composite.py
orbax/checkpoint/_src/threading.py
orbax/checkpoint/_src/arrays/abstract_arrays.py
orbax/checkpoint/_src/arrays/fragments.py
orbax/checkpoint/_src/arrays/numpy_utils.py
orbax/checkpoint/_src/arrays/sharding.py
orbax/checkpoint/_src/arrays/subchunking.py
orbax/checkpoint/_src/arrays/types.py
orbax/checkpoint/_src/checkpoint_managers/policy_checkpoint_info.py
orbax/checkpoint/_src/checkpoint_managers/preservation_policy.py
orbax/checkpoint/_src/checkpoint_managers/save_decision_policy.py
orbax/checkpoint/_src/checkpointers/abstract_checkpointer.py
orbax/checkpoint/_src/checkpointers/async_checkpointer.py
orbax/checkpoint/_src/checkpointers/checkpointer.py
orbax/checkpoint/_src/checkpointers/checkpointer_test_utils.py
orbax/checkpoint/_src/checkpointers/pytree_checkpointer.py
orbax/checkpoint/_src/checkpointers/standard_checkpointer.py
orbax/checkpoint/_src/futures/future.py
orbax/checkpoint/_src/futures/signaling_client.py
orbax/checkpoint/_src/futures/synchronization.py
orbax/checkpoint/_src/handlers/array_checkpoint_handler.py
orbax/checkpoint/_src/handlers/async_checkpoint_handler.py
orbax_checkpoint-0.11.32.dist-info/licenses/LICENSE
orbax_checkpoint-0.11.32.dist-info/WHEEL
orbax_checkpoint-0.11.32.dist-info/METADATA
orbax_checkpoint-0.11.32.dist-info/RECORD
